[
    { "id": 1, "name": "John Doe", "email": "john.doe@example.com" },
    { "id": 2, "name": "Jane Smith", "email": "jane.smith@example.com" },
    { "id": 3, "name": "Bob Johnson", "email": "bob.johnson@example.com" },
    { "id": 4, "name": "Alice Williams", "email": "alice.williams@example.com" },
    { "id": 5, "name": "Charlie Brown", "email": "charlie.brown@example.com" },
    { "id": 6, "name": "Eva Davis", "email": "eva.davis@example.com" },
    { "id": 7, "name": "Frank Miller", "email": "frank.miller@example.com" },
    { "id": 8, "name": "Grace Taylor", "email": "grace.taylor@example.com" },
    { "id": 9, "name": "Henry White", "email": "henry.white@example.com" },
    { "id": 10, "name": "Ivy Wilson", "email": "ivy.wilson@example.com" }
  ]
  